pdgid/__init__.py
pdgid/pdgid.py
pdgid/data/pdgid_data.json
pdgid-0.1.2.dist-info/LICENSE
pdgid-0.1.2.dist-info/METADATA
pdgid-0.1.2.dist-info/WHEEL
pdgid-0.1.2.dist-info/entry_points.txt
pdgid-0.1.2.dist-info/top_level.txt
pdgid-0.1.2.dist-info/RECORD
