Metadata-Version: 2.1
Name: pdgid
Version: 0.1.2
Summary: Command-line tool to get the name of a particle given its PDGID (and vice versa).
Home-page: https://gitlab.com/cardboardturkey/pdgid
Author: Kiran Ostrolenk
Author-email: kostrolenk@gmail.com
Project-URL: Bug Tracker, https://gitlab.com/CardboardTurkey/pdgid/-/issues
Keywords: particle,physics,hep,command line tool,pdg
Classifier: Programming Language :: Python :: 3
Classifier: License :: OSI Approved :: MIT License
Classifier: Operating System :: POSIX
Classifier: Intended Audience :: Science/Research
Classifier: Topic :: Scientific/Engineering :: Physics
Classifier: Topic :: System :: Shells
Requires-Python: >=3.6
License-File: LICENSE
Provides-Extra: test
Requires-Dist: black ; extra == 'test'
Requires-Dist: pylint ; extra == 'test'
Requires-Dist: pytest ; extra == 'test'
Requires-Dist: pytest-xdist ; extra == 'test'
Requires-Dist: types-setuptools ; extra == 'test'
Requires-Dist: mypy ; extra == 'test'
